{
  "name": "Mable Strickland",
  "age": 20,
  "address": {
    "street": "Wozuk Turnpike",
    "city": "Uvizedhi",
    "state": "AK",
    "zip": "07264"
  },
  "contact": {
    "phone": "(956) 824-7108",
    "servicePhone": "800696246"
  },
  "birthday": "1995-02-01T06:25:11.913Z",
  "ip": "182.222.196.176",
  "foo": "bar",
  "profile": {
    "about": "Duhtiv origu at ar dedini jaaveufu zuah di be azosurse azelubhuv nav. Eha ciojaapi jepuw mahi deovij rufojwi jezub bol uzaal oki de vihuj wa rijonek. Nu su nunazu puhrob zog ti macen ivzi dosi ji sijoglo ikiudezo ce sofe ilisoj. Heja hicpisdo if pacwoc rikem jevefe urhokfud newane ucofipur ses bim kufus uk pieggus ameweb. Amgi juetfof utojingop sohcu uznij biwonwe bilfo ke do epzabmi leun ozo mola fefgewup. Tir izumow juk hamsi gormeed tijis tiwra awe fed cospoc zoju fu nojdab em nandowgez.",
    "bio": "Cisizuwi dutiose buhewaali vin joiv ubbu nubiudu kuc vetfefah ahuzod wafmekuh ihal zalmito bedlo paocaro dinij odomorib usned. Cacinpa fo vozewaf reav vokloke ja cake igafi sepo jer binizo azeduce hig litku ka hanfonzod. Mo pon poc daeri tuf ru dujow jetorta hupahi womraz ropipi gez moafu bofucgev boakuzej lawuffi zebvub."
  },
  "apiKey": "e9085c5712431a2f7c4ca84bb8003ffc389039926366df2dda560b5f570d947f",
  "currency": {
    "code": "ALL",
    "name": "Albania Lek"
  }
}