{
  "name": "Hulda Larson",
  "age": 65,
  "address": {
    "street": "Zofo Grove",
    "city": "Vaurekis",
    "state": "NC",
    "zip": "56068"
  },
  "contact": {
    "phone": "(619) 817-7466",
    "servicePhone": "800441984"
  },
  "birthday": "1960-11-29T02:00:26.390Z",
  "ip": "89.190.203.171",
  "foo": "bar",
  "profile": {
    "about": "Hifuvora etiun rub lid jo meule cadsurwe hacanoc ebig zupot pazwa ba kitbo jez ala awoaka. Jak cowo bapozo putohwo cora niozac ceksoljek bam wafamefo azualitu buberkev ru aji luabi do go ihupevfo. Rovju nebtisug povfu irda he agenof guhagelo nitej sawwokpa ficehgav egi civok. Afdac atenercuz te jelviziw dib jud mobme ponfewpod re ubmu ehma tikife muwuzac. Gevgekod wulcaji oda pab kegkog tu muni zulfadi vahha eho vu kescec bekruv ravomko jurdimu osnudfu tov. Rupjean kaocih jijmuh ahuodu pom watru ne deoc niatasak vehuhte oriifewa asiwap atemo. Dezbefoj bowciseg gohhisid wognapig membe ri nutem nakaweco izozempah mijape daci fapibo ud siizuuvu zicazecu osiarepu.",
    "bio": "Buhkuf tewhada netil navalku il waol ba segazlih ar ezoeb usakeh kutiknim hupo va gejef hadgoh kinu kafkalufe. Zok apenic jubzorlu jodi tun kuddercov posuze cij zu logfo huza giw degog itpe kehzibciz. Raogsu cebdamve suhago hasgeufi hessilu upoedave jatejze inu nijbin odwobep gemozoh dasfe gifho gavi ucela metedfek efwa. Levrup suwut kal domebaw metumifol mecwuimu laba tah uwhub jupsakume lawpa coco vinsek sajuc taavurun odahut dovwoj. Jeldogle wi opipu ogiloaco suzwito ju kemo buabhi os heaja cut nikuguz."
  },
  "apiKey": "2f10c365a6dcc4f57b288fa275c91c8d239178f58ff54496317283ea7530c34c",
  "currency": {
    "code": "HTG",
    "name": "Haiti Gourde"
  }
}